LICENSE
MANIFEST.in
README.rst
setup.py
asyncdef.engine.egg-info/PKG-INFO
asyncdef.engine.egg-info/SOURCES.txt
asyncdef.engine.egg-info/dependency_links.txt
asyncdef.engine.egg-info/entry_points.txt
asyncdef.engine.egg-info/not-zip-safe
asyncdef.engine.egg-info/requires.txt
asyncdef.engine.egg-info/top_level.txt
asyncdef/engine/__init__.py
asyncdef/engine/core.py
asyncdef/engine/test_core.py
asyncdef/engine/processors/__init__.py
asyncdef/engine/processors/base.py
asyncdef/engine/processors/coroutine.py
asyncdef/engine/processors/selector.py
asyncdef/engine/processors/test_coroutine.py
asyncdef/engine/processors/test_selector.py
asyncdef/engine/processors/test_time.py
asyncdef/engine/processors/time.py