Metadata-Version: 1.0
Name: asyncdef.engine
Version: 0.1.0
Summary: Core event loop implementation.
Home-page: https://github.com/asyncdef/engine
Author: Kevin Conway
Author-email: kevinjacobconway@gmail.com
License: Apache 2.0
Platform: UNKNOWN
